Metadata-Version: 2.1
Name: torchdatasets-nightly
Version: 1711929801
Summary: PyTorch based library focused on data processing and input pipelines in general.
Home-page: https://github.com/szymonmaszke/torchdatasets
Author: Szymon Maszke
Author-email: szymon.maszke@protonmail.com
License: MIT
Project-URL: Website, https://szymonmaszke.github.io/torchdatasets
Project-URL: Documentation, https://szymonmaszke.github.io/torchdatasets/#torchdatasets
Project-URL: Issues, https://github.com/szymonmaszke/torchdatasets/issues?q=is%3Aissue+is%3Aopen+sort%3Aupdated-desc
Keywords: pytorch torch data datasets map cache memory disk apply database
Platform: UNKNOWN
Classifier: Development Status :: 2 - Pre-Alpha
Classifier: Programming Language :: Python
Classifier: Programming Language :: Python :: 3
Classifier: Programming Language :: Python :: 3.6
Classifier: Programming Language :: Python :: 3.7
Classifier: License :: OSI Approved :: MIT License
Classifier: Intended Audience :: Developers
Classifier: Operating System :: OS Independent
Classifier: Topic :: Scientific/Engineering
Classifier: Topic :: Software Development :: Libraries
Classifier: Topic :: Scientific/Engineering :: Artificial Intelligence
Classifier: Topic :: Software Development :: Libraries :: Python Modules
Requires-Python: >=3.6
Requires-Dist: torch >=1.2.0
